{
    "classified": [
        {
            "id": 1,
            "title": "HUGE Flat in the heart of Paris",
            "surface_area": "16 m²",
            "price": 830000,
            "description": "Twice the surface area of what you can expect for the price! An opportunity to be seized!"
        },{
            "Id": 823235244,
            "Title": "Iure nisi labore iusto fugiat repellendus.",
            "SurfaceArea": 96,
            "Price": 927715,
            "Description": "In ut. Dolor iusto. Impedit sint dolore ducimus odit sunt assumenda. Est sunt dolorum. Fuga ut facilis architecto similique voluptates ratione voluptatem."
        },
        {
            "Id": 1479488584,
            "Title": "Mollitia ex omnis hic cumque veniam.",
            "SurfaceArea": 44,
            "Price": 933466,
            "Description": "Deserunt dicta corporis voluptas aut ut. Neque et architecto nobis ipsum nam est. Quo non rerum esse voluptas ut sequi. Fugit quidem maxime eum et explicabo iste. Quasi non aliquam voluptatibus sed esse exercitationem."
        },
        {
            "Id": 906506802,
            "Title": "Ea quaerat quasi quidem placeat ullam.",
            "SurfaceArea": 78,
            "Price": 975557,
            "Description": "Reiciendis rerum nisi et veniam a dolores iusto qui amet. Incidunt iusto repellat quasi aspernatur qui laborum et. Autem vitae exercitationem repudiandae a. Et similique. Error deleniti necessitatibus dignissimos voluptates tempore qui non iste repellendus."
        },
        {
            "Id": 1170273893,
            "Title": "Vitae tempora id optio earum nihil.",
            "SurfaceArea": 75,
            "Price": 310314,
            "Description": "Neque et voluptatem molestias saepe. Eveniet ut molestiae. Dolore ab. Ut rerum impedit et repellendus non voluptas dolorum rerum eveniet. Ut facilis dolore repellat et enim voluptatem explicabo deleniti."
        },
        {
            "Id": 2032604552,
            "Title": "Blanditiis eum omnis repellendus est odit.",
            "SurfaceArea": 50,
            "Price": 189328,
            "Description": "Qui ut et fugiat consequatur velit occaecati et repudiandae. Aspernatur quo minima quisquam adipisci. Dolore aut eveniet minima. Voluptas voluptatem similique. Aut earum magnam quam incidunt quod omnis sint."
        },
        {
            "Id": 616629419,
            "Title": "Ut vel et et unde molestias.",
            "SurfaceArea": 74,
            "Price": 418314,
            "Description": "Soluta eum occaecati qui tempora. Qui corporis et debitis. Libero est reprehenderit aliquid eos velit quaerat ut eum. Tempore perspiciatis velit dolor minima et necessitatibus iusto. Aspernatur qui est quos totam amet quia."
        },
        {
            "Id": 2126343666,
            "Title": "Ad molestiae quo cum est et.",
            "SurfaceArea": 77,
            "Price": 560042,
            "Description": "Saepe asperiores tempore ipsa perspiciatis veniam consequuntur libero consequatur. Quia ad rerum ex aliquam accusamus ut omnis aspernatur. Sed et. Delectus nulla ut. Odit facere quo accusamus."
        },
        {
            "Id": 952693987,
            "Title": "Aut eveniet omnis mollitia iste ducimus.",
            "SurfaceArea": 17,
            "Price": 677299,
            "Description": "Dolorem praesentium ut pariatur beatae assumenda. Voluptatem inventore similique eveniet officia quis porro. Eum impedit velit alias consequatur sit repudiandae ipsum ut vel. Quas nisi ea odit libero modi. In nostrum laudantium qui fugit voluptas est."
        },
        {
            "Id": 1494830074,
            "Title": "Ut aut et vel qui eaque.",
            "SurfaceArea": 44,
            "Price": 198630,
            "Description": "Ab in. Dignissimos totam repudiandae nostrum autem eaque. Voluptatem nostrum nam tenetur ut tempore. Autem nihil molestias consequatur mollitia et tempora commodi recusandae numquam. Asperiores necessitatibus ratione omnis corporis nostrum illo enim tempore non."
        },
        {
            "Id": 371889853,
            "Title": "Dignissimos architecto non excepturi ut quam.",
            "SurfaceArea": 91,
            "Price": 726752,
            "Description": "Consequatur ullam maiores qui corporis provident veritatis blanditiis. Quia beatae provident optio iure eum voluptatem voluptate corrupti doloribus. Eveniet et alias est nobis. Suscipit natus. Modi porro perferendis sint rem sed."
        }
    ],
    "intermediary": [
        {
            "Id": 327009580,
            "Name": "Sint eos.",
            "Phone": "+33 (0) 2 01 04 07 03",
            "Email": "liam.moore@yopmail.com",
            "Description": "Qui vero aliquam ratione autem sapiente quis voluptatem. Provident est sapiente voluptatem. Eum nihil non ea voluptatem et quia. Ut velit. Dicta culpa rerum dolor dignissimos."
        },
        {
            "Id": 1654368365,
            "Name": "Repellat est.",
            "Phone": "+33 (0) 5 05 08 04 01",
            "Email": "guri.feng@42skillz.com",
            "Description": "Animi qui voluptatem sed unde earum rerum consequatur repellat. Et necessitatibus illo impedit nostrum vel. Sed qui iure occaecati sint. Laboriosam praesentium voluptatibus tenetur animi porro explicabo. Voluptatem minima voluptatem quo et voluptatem velit ut."
        },
        {
            "Id": 112886284,
            "Name": "At quia.",
            "Phone": "+33 (0) 7 09 09 10 10",
            "Email": "cthakur@yahoo.fr",
            "Description": "Commodi dicta consequatur reiciendis. Error doloribus. Est et. Velit est id officiis temporibus sed perferendis corporis ipsam. Quo architecto odio qui reiciendis ipsam in dolores nam."
        },
        {
            "Id": 1105522473,
            "Name": "Sequi ut.",
            "Phone": "+33 (0) 7 04 03 10 06",
            "Email": "glenn.jordan@yopmail.com",
            "Description": "Voluptatum officiis recusandae cum. Itaque voluptas unde vero nihil est aut error. Aspernatur magnam officia et maiores sequi. Similique harum dolor quia exercitationem eum soluta quidem et esse. Provident quia aut aut vel est praesentium."
        },
        {
            "Id": 893622155,
            "Name": "Natus ipsum iure.",
            "Phone": "+33 (0) 5 04 04 00 04",
            "Email": "antonio.costa@yahoo.fr",
            "Description": "Voluptates et voluptatem iste vel. Est repudiandae. Consequatur sunt. Dignissimos unde repellat accusamus et dignissimos. Minus et qui beatae."
        },
        {
            "Id": 1601076831,
            "Name": "Eos incidunt.",
            "Phone": "+33 (0) 1 02 07 01 01",
            "Email": "lin.kim@42skillz.com",
            "Description": "Beatae dolorum est. Non unde numquam quaerat atque. Ut perspiciatis veritatis. Voluptates expedita possimus. Neque tempore quia aut."
        },
        {
            "Id": 1376235085,
            "Name": "Commodi quidem a.",
            "Phone": "+33 (0) 7 03 07 06 07",
            "Email": "malka.sauba@protonmail.com",
            "Description": "Expedita provident voluptatem. Rerum pariatur non. Vel id deleniti corrupti maiores maxime cumque iste. Quasi in sunt porro maxime qui excepturi et repellendus id. Et consequatur."
        },
        {
            "Id": 2128947081,
            "Name": "Consequatur esse.",
            "Phone": "+33 (0) 4 10 03 00 00",
            "Email": "miri.johnson@ibm.com",
            "Description": "Pariatur impedit id iusto. Nihil exercitationem. Iure corrupti. Dolores placeat velit aspernatur aut aut assumenda ducimus maiores sed. Iusto architecto quasi qui itaque earum vel culpa cumque."
        },
        {
            "Id": 456393666,
            "Name": "Veritatis omnis.",
            "Phone": "+33 (0) 3 00 08 03 03",
            "Email": "irojas@42skillz.com",
            "Description": "Nam at doloremque vitae aut dolore. Molestiae sit veritatis ad nam consequatur earum assumenda aliquid soluta. Temporibus provident sequi praesentium consequuntur voluptatem fugit dignissimos hic. Non asperiores voluptatum quis ipsam in deleniti vitae repudiandae. Optio qui blanditiis omnis."
        },
        {
            "Id": 584221157,
            "Name": "Nisi sed.",
            "Phone": "+33 (0) 9 03 02 01 03",
            "Email": "esandvik@aol.com",
            "Description": "Aut ut odio exercitationem eos ut accusantium qui. Ut autem laudantium nobis odio eum odit laboriosam beatae animi. Fugit eius omnis. Architecto necessitatibus nihil. Ut aut dicta ut ad ex."
        }
    ]
}